{
  "chunk_id": "biologic-tuberoplasty_002",
  "company": "Arthrex",
  "source_id": "biologic-tuberoplasty",
  "source_type": "pdf",
  "source_title": "Biologic Tuberoplasty Surgical Technique",
  "source_url": "https://www.arthrex.com/resources/LT1-000279-en-US/biologic-tuberoplasty",
  "channel": null,
  "upload_date": null,
  "page_count": 16,
  "language": null,
  "procedure_family": "rotator_cuff",
  "product_line": "Rotator Cuff",
  "product_family": "ArthroFLEX",
  "product_name": "ArthroFLEX Dermal Allograft",
  "category": "technique_guide",
  "technique": [
    "augmentation",
    "SCR"
  ],
  "advantages": [],
  "disadvantages": [],
  "clinical_references": [],
  "chunk_index": 2,
  "chunk_count": 3,
  "word_count": 189,
  "timestamp_range": null,
  "topics": [
    "Superior Capsular Reconstruction"
  ],
  "text": "histology of a healed superior capsular reconstruction dermal allograft: a case report. Arthroscopy . 2019;35(10):2950-2958. doi:10.1016/j.arthro.2019.06.024 6. LifeNet Health. Sterile decellularized dermis instructions for use [63-0050-01]. Virginia Beach, VA; 2019. 7. LifeNet Health. Analysis of the acellular matrix, growth factors, and cytokines present in ArthroFlex® [68-20-048]. Virginia Beach, VA; 2012. US patent information Arthrex manufacturer, authorized representative, and importer information (Arthrex elFUs) This description of technique is provided as an educational tool and clinical aid to assist properly licensed medical professionals in the usage of specific Arthrex products. As part of this professional usage, the medical professional must use their professional judgment in making any final determinations in product usage and technique. In doing so, the medical professional should rely on their own training and experience, and should conduct a thorough review of pertinent medical literature and the product’s directions for use. Postoperative management is patient-specific and dependent on the treating professional’s assessment. Individual results will vary and not all patients will experience the same postoperative activity level and/or outcomes. ArthroFLEX, MatrACELL, and Preservon are registered trademarks of LifeNet Health. arthrex.com © 2023-10 Arthrex Inc. All rights reserved. LT1-000279-en-US_B"
}