{
  "chunk_id": "bony-bankart-bridge-technique-restoration-anterior-shoulder-stability_004",
  "company": "Arthrex",
  "source_id": "bony-bankart-bridge-technique-restoration-anterior-shoulder-stability",
  "source_type": "pdf",
  "source_title": "Bony Bankart Bridge Technique — Anterior Shoulder Stability",
  "source_url": "https://drmillett.com/wp-content/uploads/2017/03/bony-bankart-bridge-technique-restoration-anterior-shoulder-stability.pdf",
  "channel": null,
  "upload_date": null,
  "page_count": 7,
  "language": null,
  "procedure_family": "rotator_cuff",
  "product_line": "Shoulder",
  "product_family": "Instability",
  "product_name": "Bankart Repair",
  "category": "technique_guide",
  "technique": [
    "instability"
  ],
  "advantages": [],
  "disadvantages": [],
  "clinical_references": [],
  "chunk_index": 4,
  "chunk_count": 9,
  "word_count": 800,
  "timestamp_range": null,
  "topics": [
    "Suture anchors",
    "Shoulder instability"
  ],
  "text": "sutures through the soft tissue. (C) The medial anchor sutures are knotted, reducing the fragment together with the soft tissue. (D) Completed stable BBB repair after insertion of the lateral anchor. 610 Millett et al The American Journal of Sports Medicine at University of Minnesota Libraries on August 23, 2016ajs.sagepub.comDownloaded from of daily living, pain with sport, pain with work, pain with rest, whether patients were able to return to their sport or fitness activity), the American Shoulder and Elbow Sur- geons (ASES) score, and physical and mental components of the Short Form-12 (SF-12). Outcome measures collected at final follow-up were the Disabilities of the Arm, Shoulder and Hand–short version (QuickDASH), Single Assessment Numeric Evaluation (SANE) scores, and patient satisfac- tion, along with surgical complications. Statistical Analysis Statistical analysis was done with the use of a statistical package (SPSS version 11.0; SPSS Inc, Chicago, Illinois). The paired Student t test was used to compare the differen- ces between the preoperative and postoperative outcome measures. Univariate and nonparametric analyses were performed where appropriate for the outcome variable depending on whether the data were normally distributed. Bivariate analysis was done using a chi-square analysis. The intraclass correlation coefficient was used to measure interrater agreement between the 2 raters. The level of sig- nificance was set at P \\ .05. RESULTS The average age was 44 years (range, 24-70 years) in 2 women and 13 men. All patients reported healthy shoulders without pain or signs of instability before the initial trauma. Glenoid trauma was related to a fall while skiing, while snowboarding, or during other recreational activity in 13 of 15 (87%) of the shoulders. In 1 case, the patient was a pro- fessional kayaker who dislocated his shoulder while kayak- ing. All patients had sustained trauma-related dislocations, where the dominant shoulder was affected in 7 of 15 (47%). In 9 shoulders (60%), the arthroscopic repair was performed within 3 months (acute; range, 1-35 days) after initial injury and in 6 shoulders (40%) at a later time point (chronic; range, 120-5023 days). Among the patients within the acute group, 7 of 9 (78%) had a single dislocation, and 2 of 9 (22%) had 2 or more frank dislocations. In the chronic group, 3 of 6 patients (50%) had fewer than 10 dislocations, and 3 of 6 (50%) had 11 or more dislocations. Patients in the chronic group averaged 15 dislocations (range, 1-27) before surgery. In all patients, an osseous fragment at the anteroinfe- rior quadrant of the glenoid rim was confirmed with CT scan and during diagnostic arthroscopy (Figure 1). There was high interrater reliability in glenoid bone loss ( r = 0.968; 95% confidence interval [CI], 0.878-0.991) and depth of the Hill-Sachs lesions ( r = 0.971; 95% CI, 0.889-0.992). The mean glenoid bone loss was 29% (range, 17%-49%) of the inferior glenoid diameter. Nine patients (60%) had Hill-Sachs lesions with a depth of greater than 10%, whereas the mean maximum depth was 19% (range, 14%-27%) of the humeral head diameter. Three patients (33%) had lesions greater than 20% of the humeral head diameter. The average number of anchors used per repair to secure the glenoid fragment and labrum back into ana- tomic position was 5 (range, 4-8). Preoperative active ROM averages were forward eleva- tion 153 /C176(standard error [SE], 10 /C176), external rotation 63 /C176 (SE, 6 /C176), and external rotation at 90 /C176of abduction 78 /C176 (SE, 6 /C176). Although not statically significant, there were slight improvements in postoperative averages at a mean of 5.7 months (range, 1-18 months) to forward elevation 168/C176(SE, 3 /C176)( P = .087), external rotation 70 /C176(SE, 6 /C176)( P = .317), and external rotation at 90 /C176of abduction 86 /C176(SE, 5/C176)( P = .312). Outcome Assessment The mean subjective follow-up was 2.7 years (range, 2-4.4 years) in 13 of 15 (87%) patients. At final evaluation, the mean ASES score improved from 81.4 (range, 50-98) preop- eratively to 98.3 (range, 88-100) postoperatively ( P = .133). Although not statistically significant because of low patient numbers, the amount of improvement is almost 3 times the minimal clinically important difference of 6.4 points as reported by Michener et al. 15 The mean SF-12 (physical component) improved from 46.8 (range, 36-55.0) to 56.0 (range, 46.8-60.5) ( P = .015). Preoperative pain with activities of daily living, recreation, and sleep signifi- cantly improved for each ( P \\ .05) postoperatively. The mean QuickDASH score at final follow-up was 2.8 (range, 0-15.9) and the mean SANE score was 99 (range, 95-100). Overall, median patient satisfaction at final follow-up was 10 out of 10 points (range, 7-10). One patient who Figure 3. Final bony Bankart bridge repair with reduced bony Bankart piece, repaired labrum, and shifted capsule and inferior glenohumeral ligament complex. (Reprinted with permission from Millett PJ, Braun S. The"
}