{
  "chunk_id": "congruent-arc-latarjet-using-the-glenoid-bone-loss-set-with-375-mm-cannulated-sc_002",
  "company": "Arthrex",
  "source_id": "congruent-arc-latarjet-using-the-glenoid-bone-loss-set-with-375-mm-cannulated-sc",
  "source_type": "pdf",
  "source_title": "Congruent Arc Latarjet Using the Glenoid Bone Loss Set With 3.75 mm Cannulated Screws",
  "source_url": "https://www.arthrex.com/resources/LT1-0556-EN/congruent-arc-latarjet-using-the-glenoid-bone-loss-set-with-375-mm-cannulated-screws",
  "channel": null,
  "upload_date": null,
  "page_count": 12,
  "language": null,
  "procedure_family": "rotator_cuff",
  "product_line": "Shoulder",
  "product_family": "Instability",
  "product_name": "Bankart Repair",
  "category": "technique_guide",
  "technique": [
    "instability"
  ],
  "advantages": [],
  "disadvantages": [],
  "clinical_references": [],
  "chunk_index": 2,
  "chunk_count": 4,
  "word_count": 800,
  "timestamp_range": null,
  "topics": [
    "SutureTak",
    "Suture anchors",
    "Subscapularis",
    "Shoulder instability"
  ],
  "text": "remove the Parallel Drill Guide, leaving both wires in place. Although the 3.75 mm, fully threaded, cannulated, titanium screws are self-tapping, it is recommended to use the 2.75 mm Cannulated Drill to penetrate the near cortex of the native glenoid prior to screw insertion. Select Proper Screw The Screw Length Sizer can help determine the proper screw length. The sizer does not provide a direct measurement of the pin length. It recommends a screw length that would place the screw 5 mm short of the tip of the Guide Wire, allowing the wire to remain in position during screw insertion. Screw length is read directly from the back of the shorter, 6-inch Guide Wire, or from the laser line on the longer 7-inch Guide Wire. Note: 34 mm - 36 mm screws are commonly the correct length. Insert the Screws Place the appropriate screw over the Guide Wire and insert using the Cannulated Hex Driver. Be careful not to overtighten the screws and damage the graft. Washers are available, if desired. Remove and discard the Guide Wires. 7 Capsular Reattachment Place three BioComposite™ SutureTak® suture anchors into the native glenoid above, between and below the cannulated screws, to repair the capsule. This makes the graft an extraarticular structure and prevents its articulation directly with the humeral head, eliminating any abrasive effect of the graft against the articular cartilage of the humerus. Subscapularis Reattachment The upper half of the subscapularis tendon is typically repaired to its stump with FiberWire® alone, but suture anchors may be used, if desired. The conjoined tendon, still attached to the coracoid graft, exits anteriorly through the split between the upper and lower halves of the subscapularis tendon. It is not necessary to reattach the pectoralis minor to the residual coracoid base or adjacent soft tissues because it does not retract. After subscapularis repair, a standard skin closure is performed. Postoperative Rehabilitation The patient uses a sling for four to six weeks, with external rotation restricted to zero degrees (0°). At this point, the sling is discontinued and overhead motion is encouraged. Gentle external rotation stretching is begun at six weeks postoperative. The goal at three months postoperative is for the external rotation on the operated shoulder to be half that of the opposite shoulder. Strengthening exercises are delayed until three months postoperative, at which time the bone graft usually shows early radiographic evidence of consolidation with the glenoid. Contact sports or heavy labor are generally allowed when the graft appears radiographically healed to the glenoid, which is usually six to 12 months postoperative. Coracoid graft Suture anchor Anterior capsule Subscapularis muscle Conjoined tendon Anterior capsule Coracoid graft 8 Bony Bankart/Glenoid Fracture Surgical Technique The instrument set has been designed to allow placement of the partially threaded 3.75 mm cannulated screws either percutaneously or through a standard arthroscopic cannula. Insert the long Nesting Guide Sleeve through a stab incision or arthroscopic cannula and place on the bone. Insert the long, 12-inch, 1.6 mm, nonthreaded, Guide Wire through the fracture fragment and into the glenoid. The 3.75 mm, partially threaded, cannulated, titanium screws are self-drilling and self-tapping. In dense bone, it may be helpful to use the 2.75 mm Cannulated Drill. Remove the inner sleeve and use the 2.75 mm Cannulated Drill to prepare the pilot hole. Measure for proper screw length before removal of the second nesting guide. The Screw Length Sizer does not provide a direct measurement of the Guide Wire position. It recommends a screw length that would place the screw 5 mm short of the tip of the Guide Wire, allowing the Guide Wire to remain in position during screw insertion. Make sure that the Nesting Guide Sleeve is in contact with the bone and that the Screw Length Sizer is in contact with the second nesting guide. Read the recommended screw length directly from the back of the Guide Wire. Remove the inner nesting guide and use the Cannulated Hex Driver to place the proper screw over the Guide Wire. Remove and discard the Guide Wire. 5 mm 9 Ordering Information Glenoid Bone Loss Set AR-7000S Set includes: Osteotome Blade Shield AR-7000-02 Parallel Drill Guide, 4 mm offset AR-7000-03 Parallel Drill Guide, 6 mm offset AR-7000-04 Parallel Drill Guide, 8 mm offset AR-7000-05 Screw Length Sizer AR-7000-06 Coracoid Drill Guide AR-7000-07 Fukuda Retractor, small AR-7000-08 Glenoid Retractor AR-7000-09 Nesting Guide Sleeves AR-7000-12 Cannulated Hex Driver, 2.5 mm AR-7000-13 Cannulated Drill, 2.75 mm AR-7000-14 Drill, noncannulated, 4 mm AR-1204D 10 Ordering Information Osteotome Handle AR-2961 Drill Guide Handle AR-9215-1-01 Cannulated Driver Handle w/AO Connection AR-13221AOC Gelpi Retractor AR-8104 (not pictured) Glenoid Bone Loss Instrument Case AR-7000C Screw Caddy, 3.75 mm, Fully Threaded Screw AR-7000SC-1 Screw Caddy, 3.75 mm, Partially Threaded Screw AR-7000SC-2 Disposables Osteotome Blade, Latarjet AR-7000-01 (not pictured) .062” (1.6 mm) Guide Wire,"
}