{
  "chunk_id": "content-29e3e01c19e206a3bf-ajo045070320_000",
  "source_id": "content-29e3e01c19e206a3bf-ajo045070320",
  "source_type": "pdf",
  "source_title": "The Arthroscopic Superior Capsular Reconstruction (AJO)",
  "source_url": "https://cdn.mdedge.com/files/s3fs-public/issues/articles/content_29e3e01c19e206a3bf_ajo045070320.PDF",
  "channel": null,
  "upload_date": null,
  "page_count": 5,
  "language": null,
  "procedure_family": "rotator_cuff",
  "chunk_index": 0,
  "chunk_count": 5,
  "word_count": 800,
  "timestamp_range": null,
  "topics": [
    "Superior Capsular Reconstruction",
    "Subscapularis",
    "Supraspinatus",
    "Infraspinatus",
    "Biceps tenodesis",
    "Shoulder instability",
    "Rotator cuff repair",
    "Shoulder arthroplasty"
  ],
  "text": "320 The American Journal of Orthopedics ® July/August 2016 www.amjorthopedics.com Tips of the Trade The Arthroscopic Superior Capsular Reconstruction Christopher R. Adams, MD, Patrick J. Denard, MD, Paul C. Brady, MD, Robert U. Hartzler, MD, and Stephen S. Burkhart, MD R otator cuff tears are very common, and 250,000 to 500,000 rotator cuff repairs are performed in the United States each year.1,2 In most cases, a complete repair of even large or massive tears can be achieved. How - ever, a subset of patients exist in whom the glenohumeral joint has minimal degenerative changes and the rotator cuff tendon is either irreparable or very poor quality and unlikely to heal (ie, failed previous cuff repair). Some authors have advocated for reverse shoulder arthroplasty (RSA) in these patients despite the lack of glenohumeral arthritis. However, due to the permanent destruction of the glenohumer - al articular surfaces, complication rates, and concerns about implant longevity with RSA, we believe the superior capsular reconstruction (SCR) is a viable alternative in patients in whom joint preservation is appropriate based on age limitations and/or activity requirements. 3 The SCR was first described by Mihata and colleagues 4 as a means to reconstruct the supe - rior capsule in shoulders with large, irreparable posterosuperior rotator cuff tears. Originally described using a fascia lata autograft, our technique has been adapted to incorporate a dermal allograft, which limits donor site mor - bidity and operative time. In most cases, the dermal allograft is fixed to the normal anatomic attachments of the superior glenoid just medial to the superior labrum, laterally to the greater tuberosity, and posteriorly with side-to-side sutures to the remaining rotator cuff. If there is a robust band of “comma” tissue anteriorly, we fix the anterior margin of the dermal graft to this with side-to-side sutures. The comma tissue represents the medial sling of the biceps tendon and connects the upper subscapularis tendon to the anterior supraspinatus. In most cases, this tissue is intact after repair of the subscapularis tendon. Technique The patient is positioned in either the lateral decubitus or beach chair position. The arm is positioned in 20° to 30° of abduction and 20° to 30° of forward flexion. A diagnostic arthroscopy is performed through a posterior glenohumeral viewing portal. The subscapularis is visualized and repaired if torn. A biceps tenodesis is per - formed in most cases, as there is often a tear of the subscapularis, tear or instability of the bi - ceps tendon, and/or a compromised attachment of the biceps root. Attention is turned to the subacromial space. Posterior viewing and lateral working portals are established. A 10-mm flexible cannula (PassPort; Arthrex) is placed in the lateral portal to aid with suture management and graft passage. A limited subacromial decompression is performed that preserves the coracoacromial arch. The rotator cuff is carefully dissected and freed from the Abstract In a subset of patients with rotator cuff tears, the glenohumeral joint has minimal degenerative changes and the rotator cuff tendon is either irreparable or very poor quality and unlikely to heal. Reverse shoulder arthroplasty (RSA) is often considered for these patients despite the lack of glenohumeral arthritis. However, due to the permanent destruction of the glenohumeral articular surfaces, compli- cation rates, and concerns about implant longevity with RSA, we believe the superior capsular reconstruction (SCR) is a viable alternative. In this article, we describe our technique for the SCR. Authors’ Disclosure Statement: Dr. Adams reports that he is an employee of Arthrex. Dr. Denard reports that he is a consultant to and receives research support from Arthrex. Dr. Brady reports that he is a consultant to and on the speaker’s bureau for Arthrex. Dr. Hartzler reports that he is on the speaker’s bureau for Arthrex. Dr. Burkhart reports that he is a consultant to and receives royalties from Arthrex. www.amjorthopedics.com July/August 2016 The American Journal of Orthopedics® 321 internal deltoid fascia. The scapular spine is iden - tified to visualize the raphé between the supra - spinatus and infraspinatus. The infraspinatus is mobilized and repaired as much as possible. If we think that the tear might be reparable by gaining added excursion from a posterior interval slide, or if it is clearly not reparable but the remaining rim of rotator cuff obscures clear visualization of the superior glenoid, we per - form a posterior interval slide. If the additional excursion that is achieved by the posterior slide is adequate for a complete repair, we proceed with the repair. However, if the tear is not repa - rable even after the posterior interval slide, we have found that the exposure and preparation of the superior glenoid is greatly improved after the posterior slide. After fixation of the dermal graft, we typically perform a partial side-to-side repair of the supraspinatus to the infraspinatus over"
}