{
  "chunk_id": "remplissage-for-anterior-instability-scientific-update_003",
  "company": "Arthrex",
  "source_id": "remplissage-for-anterior-instability-scientific-update",
  "source_type": "pdf",
  "source_title": "Remplissage for Anterior Instability Scientific Update",
  "source_url": "https://www.arthrex.com/resources/DOC1-000498-en-US/remplissage-for-anterior-instability-scientific-update",
  "channel": null,
  "upload_date": null,
  "page_count": 8,
  "language": null,
  "procedure_family": "rotator_cuff",
  "product_line": "Shoulder",
  "product_family": "Instability",
  "product_name": "Bankart Repair",
  "category": "clinical_study",
  "technique": [
    "instability"
  ],
  "advantages": [],
  "disadvantages": [],
  "clinical_references": [],
  "chunk_index": 3,
  "chunk_count": 4,
  "word_count": 409,
  "timestamp_range": null,
  "topics": [
    "Shoulder instability"
  ],
  "text": "remplissage in anterior shoulder instability results in fewer redislocations than Bankart repair alone at medium-term follow-up of a randomized controlled trial. Am J Sports Med . 2024;52(8):2055-2062. doi:10.1177/03635465241254063 ■ Medium-term (3- to 9-year) follow-up of a randomized controlled trial of arthroscopic Bankart versus remplissage in patients with <15% glenoid bone loss • 52 isolated Bankarts • 50 remplissages ■ Recurrent dislocation was observed in 22% of Bankarts compared to 7.7% of remplissages ■ Recurrent instability (dislocation or subluxation) was observed in 30% of Bankarts compared to 9.6% of remplissages Takeaway Remplissage reduces risk of recurrent dislocation or instability events by approximately 3× compared to isolated Bankart repair in patients with <15% glenoid bone loss Ahmed AF, Polisetty TS, Wang C, Halayqeh S, Sharma S, Miller AS, Pearson Z, Fajolu O, Zikria B, Srikumaran U Higher return to sport and lower revision rates when performing arthroscopic Bankart repair with remplissage for anterior shoulder instability with a Hill-Sachs lesion: a meta-analysis. J Shoulder Elbow Surg. 2024. doi:10.1016/j.jse.2024.01.045 ■ Meta-analysis of 12 studies in patients with <25% glenoid bone loss, including: • 550 isolated Bankarts • 347 remplissages ■ External rotation at the side was only 1° lower after remplissage, which is not a clinically significant difference ■ The odds of recurrent dislocation were 6.3× higher after isolated Bankart repair ■ Return to sport was 2.9× higher after remplissage Takeaway There is no clinically meaningful difference in postoperative external rotation after isolated Bankart repair compared to remplissage Return to sport is higher after remplissage compared to isolated Bankart arthrex.com © 2025-02 Arthrex, Inc. All rights reserved. DOC1-000498-en-US_C Gonzalez-Morgado D, Ardebol J, Noble MB, Galasso LA, Menendez ME, Denard PJ No difference in external rotation loss after isolated Bankart repair, remplissage, or Latarjet: a systematic review and meta-analysis. Am J Sports Med . 2025;53(2):493-500. doi:10.1177/03635465241241825 ■ Meta-analysis of 27 studies in 2100 patients including: • 824 isolated Bankart repairs • 378 Bankart + remplissage • 898 Latarjet procedures ■ External rotation at the side recorded for each study and pooled for analysis • Mean differences: - Bankart vs Bankart + remplissage: 5.9° ( P = .13) - Remplissage vs Latarjet: 9.6° ( P = .17) ■ Recurrence was 6.7× higher after isolated Bankart compared to the addition of remplissage (P = .4) Takeaways There is no clinically meaningful difference in postoperative external rotation after isolated Bankart repair, remplissage, or Latarjet Recurrence is 6.7× higher with isolated Bankart compared to the addition of remplissage"
}