{
  "chunk_id": "shoulder-and-elbow-next-generation-in-repair-and-reconstruction_013",
  "company": "Arthrex",
  "source_id": "shoulder-and-elbow-next-generation-in-repair-and-reconstruction",
  "source_type": "pdf",
  "source_title": "Shoulder and Elbow: Next Generation in Repair and Reconstruction",
  "source_url": "https://www.arthrex.com/resources/LB1-0220-EN/shoulder-and-elbow-next-generation-in-repair-and-reconstruction",
  "channel": null,
  "upload_date": null,
  "page_count": 114,
  "language": null,
  "procedure_family": "rotator_cuff",
  "product_line": "Rotator Cuff",
  "product_family": "FiberTape",
  "product_name": "FiberTape",
  "category": "technique_guide",
  "technique": [],
  "advantages": [],
  "disadvantages": [],
  "clinical_references": [],
  "chunk_index": 13,
  "chunk_count": 44,
  "word_count": 800,
  "timestamp_range": null,
  "topics": [
    "Knotless fixation"
  ],
  "text": "14 in #2 tails and 36.6 mm ½ circle tapered needle (white/blue/black) AR-7274TT (a) (b) (c) (d) (e) FiberWire® Suture I 29 FiberWire® and TigerWire® Sutures FiberWire suture is constructed of a multistranded long chain ultra-high–molecular weight polyethylene (UHMWPE) core with a braided jacket of polyester and UHMWPE that gives FiberWire suture superior strength, 1 soft feel, and abrasion resistance 2 that is unequaled in orthopedic surgery. Suture breakage during knot tying is virtually eliminated, especially critical during arthroscopic procedures. 3 Product Description Item Number #5 FiberWire Suture, 38 in (blue) AR-7210 #5 FiberWire Suture, 38 in (blue) w/ conventional cutting needle, 48 mm, ½ circle AR-7211 #5 FiberWire Suture, 38 in (1 blue, 1 white, 1 white/black) w/ conventional cutting needle, 48 mm, ½ circle AR-7212 #5 FiberWire Suture, 38 in (blue) w/ conventional cutting needle, 48 mm, ½ circle, and tapered needle, 26.5 mm, ½ circle AR-7213 #5 FiberWire Suture, 38 in (white) AR-7215 #2 FiberWire Suture, 38 in (blue) w/ tapered needle, 26.5 mm, ½ circle AR-7200 #2 FiberWire Suture, 38 in (blue) w/ tapered needle, 26.5 mm, ½ circle, collagen-coated AR-7200B #2 FiberWire Suture, 38 in (blue) w/ reverse cutting needle, 36.6 mm, ½ circle AR-7202 #2 FiberWire Suture, 38 in (blue) w/ two tapered needles, 26.5 mm ½ circle AR-7205 #2 TigerWire Suture, 38 in (white/black) w/ two tapered needles, 26.5 mm, ½ circle AR-7205T #2 FiberWire Suture, 38 in (blue) w/ tapered needle, 36.6 mm, ½ circle AR-7206 #2 FiberWire Suture, 38 in (1 blue, 1 white/black) w/ tapered needle, 26.5 mm, ½ circle AR-7208 #2 FiberWire Suture, 38 in (1 blue, 1 white/black) w/ reverse cutting needle, 36.6 mm, ½ circle AR-7217 #2 FiberWire Suture, 38 in (blue) w/ diamond-point needle, straight AR-7246 #2 FiberWire Suture, 38 in (blue) w/ two diamond- point needles, straight AR-7246-02 #2 FiberWire Suture, 38 in (blue) AR-7233 #2 TigerWire Suture, 38 in (white/black) AR-7203 #2 FiberWire Suture, 38 in (1 blue, 1 white/black) AR-7201 #2 FiberWire Suture, 38 in (1 white, 1 blue/black) AR-7240 Product Description Item Number #1 FiberWire Suture, 38 in (blue) AR-7216 0 FiberWire Suture, 38 in (blue) AR-7254 0 FiberWire Suture, 38 in (white) AR-7255 0 FiberWire Suture, 38 in (blue) w/ tapered needle, 22.2 mm, ½ circle AR-7250 0 FiberWire Suture, 38 in (blue) w/ diamond point needle, 22.2 mm, ½ circle AR-7251 FiberWire suture Kit AR-7219 Includes four #5 FiberWire (blue), four #5 FiberWire (white), four #5 FiberWire (white/black), and six #2 FiberWire (blue) sutures w/ tapered needle and 3 free needles Collagen-Coated FiberWire Suture Collagen-coated FiberWire suture is coated with type I bovine collagen, offering a softer coating and improved handling characteristics. These sutures are ideal for knotted and knotless repairs. Product Description Item Number #2 FiberWire Suture, 38 in w/ tapered needle, 26.5 mm, ½ circle, collagen-coated AR-7200B #2 FiberLoop® Suture w/ straight needle, 20 in (blue), 76 mm needle w/ 7 mm loop, collagen-coated AR-7234B FiberTape® Suture, 2 mm, 7 in (blue) tape w/ each end tapered to #2 FiberWire suture, 30 in, collagen-coated AR-7237-7B References 1. Wüst DM, Meyer DC, Favre P, Gerber C. Mechanical and handling properties of braided polyblend polyethylene sutures in comparison to braided polyester and monofilament polydioxanone sutures. Arthroscopy . 2006;22(11):1146-1153. doi:10.1016/j.arthro.2006.06.013. 2. Lo IK, Burkhart SS, Athanasiou K. Abrasion resistance of two types of nonabsorbable braided suture. Arthroscopy . 2004;20(4):407-413. doi:10.1016/j. arthro.2004.01.022. 3. Lo IK, Burkhart SS, Chan KC, Athanasiou K. Arthroscopic knots: determining the optimal balance of loop security and knot security. Arthroscopy . 2004;20(5):489- 502. doi:10.1016/j.arthro.2004.03.005. 30 I FiberWire® Suture FiberTape® Suture Ultra-high–strength 2 mm and 1.7 mm FiberTape sutures have a similar long-chain polyethylene structure as FiberWire® suture. In addition to high-demand applications, like AC joint reconstruction, the broad footprint of FiberTape suture is ideal for repairs where tissue pull-through may be a concern. Product Description Item Number FiberTape Suture, 2 mm, 36 in (blue), each end tapered to #2 FiberWire suture AR-7237 FiberTape Suture, 2 mm, 7 in (blue), each end tapered to #2 FiberWire suture (d) AR-7237-7 FiberTape Suture, 2 mm, 7 in (blue), each end tapered to #2 FiberWire suture, collagen-coated AR-7237-7B FiberTape Suture, 2 mm, 17 in (blue), each end tapered to #2 FiberWire suture w/ tapered needle 26.5 mm, ½ circle AR-7237-17N TigerTape™ Suture, 2 mm, 7 in (white/black), each end tapered to #2 FiberWire suture (b) AR-7237-7T FiberTape Suture, 1.7 mm, 36 in (blue), each end tapered to 0 FiberWire suture AR-7273 TigerTape Suture, 1.7 mm, 36 in (white/black), each end tapered to 0 FiberWire suture AR-7273T FiberTape Suture, 1.7 mm, 8 in working length, 30 in overall (blue), each end tapered to 0 FiberWire suture (c) AR-7273-8 TigerTape Suture, 1.7 mm, 8 in working length, 30 in overall (white/black), each end tapered to 0 FiberWire suture (a) AR-7273-8T FiberTape Suture, 1.7 mm,"
}