{
  "chunk_id": "TMytPkQeblM_000",
  "source_id": "TMytPkQeblM",
  "source_type": "youtube",
  "source_title": "Knotless Shoulder Labral Repair with Arthrex® PushLock®",
  "source_url": "https://www.youtube.com/watch?v=TMytPkQeblM",
  "channel": "Arthrex",
  "upload_date": "20170209",
  "page_count": null,
  "language": "en",
  "procedure_family": "rotator_cuff",
  "chunk_index": 0,
  "chunk_count": 1,
  "word_count": 177,
  "timestamp_range": {
    "start_seconds": 1.04,
    "end_seconds": 103.88,
    "label": "00:00:01-00:01:43"
  },
  "topics": [
    "PushLock",
    "Knotless fixation",
    "Suture anchors",
    "Shoulder instability"
  ],
  "text": "the push lock is a device designed to repair cartilage tears in the shoulder the surgeon Begins by identifying the cartilage tear and inserting two canulas into the shoulder a suture passing device is placed between the cartilage or laum and the shoulder socket or glenoid a looped wire is passed underneath the laum and retrieved through the anterior canula a suture is shuttled around the laum using the wire the suture is retrieved and a drill is inserted into the joint the drill is used to create a bone socket on the glenoid the sutures are fed through a knotless push loock anchor and the anchor is hammered into the socket securing the labrum to the Bone alternatively the looped wire can be eliminated and the suture passed directly underneath the labrum it is fed into the joint and the end is retrieved with a grasping instrument another socket is drilled and the suture is fed through the push lock anchor and hammered into place typically a surgeon will use three anchors for a cartilage repair"
}